Spdex-0.0.3.dist-info/METADATA
Spdex-0.0.3.dist-info/RECORD
Spdex-0.0.3.dist-info/WHEEL
Spdex-0.0.3.dist-info/top_level.txt
spdex/VERSION.txt
spdex/__init__.py
spdex/crawl.py
spdex/info.py
spdex/m_test.py
spdex/spider.py
