Metadata-Version: 2.1
Name: Spdex
Version: 0.0.3
Summary: download lottery data
Home-page: https://iseuwei.000webhostapp.com/
Author: Iseuwei
Author-email: iseu1130@sina.cn
License: BSD
Keywords: spdex,lottery ticket
Platform: UNKNOWN
Classifier: Development Status :: 4 - Beta
Classifier: Programming Language :: Python :: 3.5
Classifier: License :: OSI Approved :: BSD License
Requires-Dist: pandas (>=0.18.0)
Requires-Dist: requests (>=2.0.0)
Requires-Dist: pymongo (>=3.7.1)
Requires-Dist: beautifulsoup4 (>=4.8.1)
Requires-Dist: PyYAML (>=5.1.2)
